AUTHORS
LICENSE
MANIFEST.in
README.rst
setup.py
partialize/__init__.py
partialize/arguments.py
partialize/decorator.py
partialize/exceptions.py
partialize.egg-info/PKG-INFO
partialize.egg-info/SOURCES.txt
partialize.egg-info/dependency_links.txt
partialize.egg-info/top_level.txt