Metadata-Version: 1.0
Name: partialize
Version: 0.0.3
Summary: Python partial on steroids
Home-page: https://github.com/5monkeys/partialize
Author: Jonas Lundberg
Author-email: jonas@5monkeys.se
License: MIT
Download-URL: https://github.com/5monkeys/partialize/tarball/v0.0.3
Keywords: partial,functools,args,kwargs,keywords,arguments
Platform: any
Classifier: Programming Language :: Python
Classifier: Natural Language :: English
Classifier: Intended Audience :: Developers
Classifier: License :: OSI Approved :: MIT License
Classifier: Operating System :: OS Independent
Classifier: Topic :: Utilities
Classifier: Topic :: Software Development :: Libraries :: Python Modules
